psq/__init__.py
psq/broadcast_queue.py
psq/broadcast_queue_test.py
psq/datastore_storage.py
psq/datastore_storage_test.py
psq/globals.py
psq/psqworker.py
psq/queue.py
psq/queue_test.py
psq/storage.py
psq/storage_test.py
psq/task.py
psq/task_test.py
psq/utils.py
psq/worker.py
psq/worker_test.py
psq-0.8.0.dist-info/LICENSE
psq-0.8.0.dist-info/METADATA
psq-0.8.0.dist-info/WHEEL
psq-0.8.0.dist-info/entry_points.txt
psq-0.8.0.dist-info/top_level.txt
psq-0.8.0.dist-info/RECORD
