Metadata-Version: 2.1
Name: psq
Version: 0.8.0
Summary: A simple task queue using Google Cloud Pub/Sub
Home-page: https://github.com/GoogleCloudPlatform/psq
Author: Thea Flowers
Author-email: theaflowers@google.com
License: Apache Software License
Keywords: queue tasks background worker
Platform: UNKNOWN
Classifier: Development Status :: 3 - Alpha
Classifier: Intended Audience :: Developers
Classifier: Topic :: Software Development :: Libraries :: Python Modules
Classifier: Topic :: Internet
Classifier: Topic :: Scientific/Engineering
Classifier: Topic :: System :: Distributed Computing
Classifier: License :: OSI Approved :: Apache Software License
Classifier: Programming Language :: Python
Classifier: Programming Language :: Python :: 2
Classifier: Programming Language :: Python :: 3
Classifier: Programming Language :: Python :: 2.7
Classifier: Programming Language :: Python :: 3.5
Classifier: Programming Language :: Python :: 3.6
Classifier: Operating System :: POSIX
Classifier: Operating System :: MacOS
Classifier: Operating System :: Unix
Requires-Dist: google-cloud-pubsub (>=0.35.2)
Requires-Dist: google-cloud-datastore (<=2.0.0,>=1.0.0)
Requires-Dist: werkzeug (<1.0.0,>=0.10.0)
Requires-Dist: click (>=4.0)
Requires-Dist: colorlog (<3.0.0,>=2.6.0)
